Metadata-Version: 2.1
Name: CryptDrive
Version: 0.1.2
Summary: A Simple Encryption Tool that also saves and retreive files from Google Drive with OneLine-Commands
Home-page: https://github.com/revanrohith/CryptDrive
Author: revanrohith
Author-email: revanrohith@gmail.com
License: UNKNOWN
Platform: UNKNOWN
Classifier: Programming Language :: Python :: 3
Classifier: License :: OSI Approved :: Apache Software License
Classifier: Operating System :: OS Independent
Requires-Python: >=3.6
